{"nodes": [{"id": "landing_editorial_placements_roadmap", "label": "Landing Editorial Placements Roadmap", "file_type": "document", "source_file": "LANDING_EDITORIAL_PLACEMENTS_ROADMAP.md", "source_location": null, "source_url": null, "captured_at": null, "author": null, "contributor": null}, {"id": "concept_editorial_placements", "label": "Editorial Placements Pattern", "file_type": "rationale", "source_file": "LANDING_EDITORIAL_PLACEMENTS_ROADMAP.md", "source_location": null, "source_url": null, "captured_at": null, "author": null, "contributor": null}, {"id": "concept_null_equals_empty", "label": "null = slot empty Rule", "file_type": "rationale", "source_file": "LANDING_EDITORIAL_PLACEMENTS_ROADMAP.md", "source_location": null, "source_url": null, "captured_at": null, "author": null, "contributor": null}, {"id": "concept_declarative_editorial_model", "label": "Declarative Editorial Model", "file_type": "concept", "source_file": "LANDING_EDITORIAL_PLACEMENTS_ROADMAP.md", "source_location": null, "source_url": null, "captured_at": null, "author": null, "contributor": null}, {"id": "concept_firebase_editorial_placements_collection", "label": "Firestore editorialPlacements Collection", "file_type": "concept", "source_file": "LANDING_EDITORIAL_PLACEMENTS_ROADMAP.md", "source_location": null, "source_url": null, "captured_at": null, "author": null, "contributor": null}], "edges": [{"source": "landing_editorial_placements_roadmap", "target": "concept_editorial_placements", "relation": "implements", "confidence": "EXTRACTED", "confidence_score": 1.0, "source_file": "LANDING_EDITORIAL_PLACEMENTS_ROADMAP.md", "source_location": "landing editorial document schema v2", "weight": 1.0}, {"source": "concept_editorial_placements", "target": "concept_firebase_editorial_placements_collection", "relation": "implements", "confidence": "EXTRACTED", "confidence_score": 1.0, "source_file": "LANDING_EDITORIAL_PLACEMENTS_ROADMAP.md", "source_location": "editorialPlacements Firestore collection", "weight": 1.0}, {"source": "landing_editorial_placements_roadmap", "target": "concept_null_equals_empty", "relation": "rationale_for", "confidence": "EXTRACTED", "confidence_score": 1.0, "source_file": "LANDING_EDITORIAL_PLACEMENTS_ROADMAP.md", "source_location": "null = slot empty core rule", "weight": 1.0}, {"source": "landing_editorial_placements_roadmap", "target": "concept_declarative_editorial_model", "relation": "implements", "confidence": "EXTRACTED", "confidence_score": 1.0, "source_file": "LANDING_EDITORIAL_PLACEMENTS_ROADMAP.md", "source_location": "declarative editorial model with null/manual/auto-* modes", "weight": 1.0}, {"source": "concept_declarative_editorial_model", "target": "concept_null_equals_empty", "relation": "rationale_for", "confidence": "EXTRACTED", "confidence_score": 1.0, "source_file": "LANDING_EDITORIAL_PLACEMENTS_ROADMAP.md", "source_location": "null = slot empty is the foundational rule of declarative editorial model", "weight": 1.0}], "hyperedges": []}